esb_smart_meter_importer/__init__.py
esb_smart_meter_importer/exceptions.py
esb_smart_meter_importer/importer.py
esb_smart_meter_importer-0.2.0.dist-info/LICENSE
esb_smart_meter_importer-0.2.0.dist-info/METADATA
esb_smart_meter_importer-0.2.0.dist-info/WHEEL
esb_smart_meter_importer-0.2.0.dist-info/RECORD
