Metadata-Version: 2.1
Name: esb-smart-meter-importer
Version: 0.2.0
Summary: A small utility to extract power comsumption data from Ireland's national electrical grid provider.
Author: Thomas Dunne
Author-email: thomasdunne999@gmail.com
Requires-Python: >=3.8,<4.0
Classifier: Programming Language :: Python :: 3
Classifier: Programming Language :: Python :: 3.8
Classifier: Programming Language :: Python :: 3.9
Classifier: Programming Language :: Python :: 3.10
Classifier: Programming Language :: Python :: 3.11
Classifier: Programming Language :: Python :: 3.12
Requires-Dist: beautifulsoup4 (>=4.12.2,<5.0.0)
Requires-Dist: requests (>=2.31.0,<3.0.0)
